{"Name": "user1", "Operation": [{"operation": "Replenish the balance"}, {"operation": "Check your balance"}, {"operation": "Replenish the balance"}, {"operation": "Check your balance"}, {"operation": "Check your balance"}, {"operation": "Withdraw money from account"}, {"operation": "Check your balance"}, {"operation": "Withdraw money from account"}, {"operation": "Check your balance"}, {"operation": "Check your balance"}, {"operation": "Withdraw money from account"}, {"operation": "Check your balance"}, {"operation": "Check your balance"}, {"operation": "Check your balance"}, {"operation": "Check your balance"}, {"operation": "Withdraw money from account"}, {"operation": "Check your balance"}]}